LICENSE.txt
MANIFEST.in
README.rst
requirements.txt
setup.cfg
setup.py
versioneer.py
dask_drmaa/__init__.py
dask_drmaa/_version.py
dask_drmaa/adaptive.py
dask_drmaa/core.py
dask_drmaa/sge.py
dask_drmaa.egg-info/PKG-INFO
dask_drmaa.egg-info/SOURCES.txt
dask_drmaa.egg-info/dependency_links.txt
dask_drmaa.egg-info/entry_points.txt
dask_drmaa.egg-info/not-zip-safe
dask_drmaa.egg-info/requires.txt
dask_drmaa.egg-info/top_level.txt
dask_drmaa/cli/dask_drmaa.py