Metadata-Version: 1.2
Name: dask-drmaa
Version: 0.2.0
Summary: Dask on DRMAA
Home-page: http://github.com/dask/dask-drmaa/
Maintainer: Matthew Rocklin
Maintainer-email: mrocklin@gmail.com
License: BSD
Platform: UNKNOWN
